metasnek/__init__.py
metasnek/fasta_finder.py
metasnek/fastq_finder.py
metasnek-0.0.8.dist-info/LICENSE
metasnek-0.0.8.dist-info/METADATA
metasnek-0.0.8.dist-info/WHEEL
metasnek-0.0.8.dist-info/top_level.txt
metasnek-0.0.8.dist-info/RECORD
