Metadata-Version: 2.1
Name: metasnek
Version: 0.0.8
Summary: Misc functions for metagenomics pipelines
Home-page: https://github.com/beardymcjohnface/metasnek
Author: Michael Roach
Author-email: beardymcjohnface@gmail.com
Requires-Python: >=3.8
License-File: LICENSE
